[{"title": "两市融资余额减少27.80亿元，融资客交易活跃度上升", "link": "https://36kr.com/newsflashes/2278186048001801?f=rss", "pubDate": "2023-05-29 08:50:41"}, {"title": "安信证券：TMT第二波正在酝酿开启", "link": "https://36kr.com/newsflashes/2278163339745027?f=rss", "pubDate": "2023-05-29 08:45:27"}, {"title": "“晶捷科技”获1.5亿元A轮融资", "link": "https://36kr.com/newsflashes/2278176842225412?f=rss", "pubDate": "2023-05-29 08:41:19"}, {"title": "中金公司：四大指标初步提示A股偏底部特征，当前位置不必悲观", "link": "https://36kr.com/newsflashes/2278175794911235?f=rss", "pubDate": "2023-05-29 08:40:15"}, {"title": "核电产业暖春归来：新项目核准重回正轨，制造订单再现高峰", "link": "https://36kr.com/newsflashes/2278174902425601?f=rss", "pubDate": "2023-05-29 08:39:21"}, {"title": "东风汽车：东风武汉轻型汽车有限公司与公司无任何股权关系和业务往来", "link": "https://36kr.com/newsflashes/2278172622755590?f=rss", "pubDate": "2023-05-29 08:37:01"}, {"title": "下半年H100鸿海代工比重升至九成，A100以纬创为主", "link": "https://36kr.com/newsflashes/2278162410690312?f=rss", "pubDate": "2023-05-29 08:35:32"}, {"title": "招商证券：A股“N“型最后一个拐点或将出现", "link": "https://36kr.com/newsflashes/2278170756585221?f=rss", "pubDate": "2023-05-29 08:35:08"}, {"title": "“华谱科仪”获亿元A轮融资", "link": "https://36kr.com/newsflashes/2278169641064455?f=rss", "pubDate": "2023-05-29 08:34:00"}, {"title": "多地加速废止圈而不建风光项目", "link": "https://36kr.com/newsflashes/2278161067874305?f=rss", "pubDate": "2023-05-29 08:25:16"}, {"title": "容百科技：与亿纬锂能签订《战略合作协议》并达成战略伙伴关系", "link": "https://36kr.com/newsflashes/2278159650854656?f=rss", "pubDate": "2023-05-29 08:23:50"}, {"title": "安徽：公务用车原则上全部购置新能源汽车", "link": "https://36kr.com/newsflashes/2278157360928775?f=rss", "pubDate": "2023-05-29 08:21:30"}, {"title": "“三年持有”基金回报分化显著", "link": "https://36kr.com/newsflashes/2278156875716608?f=rss", "pubDate": "2023-05-29 08:21:00"}, {"title": "四川省委书记王晓晖调研天齐锂业奎纳纳氢氧化锂生产基地", "link": "https://36kr.com/newsflashes/2278156094986246?f=rss", "pubDate": "2023-05-29 08:20:13"}, {"title": "信托分类改革6月起正式实施，四川信托等加快风险处置", "link": "https://36kr.com/newsflashes/2278155393226500?f=rss", "pubDate": "2023-05-29 08:19:30"}, {"title": "上市公司理财降温，投资总额同比降四成", "link": "https://36kr.com/newsflashes/2278154264827910?f=rss", "pubDate": "2023-05-29 08:18:21"}, {"title": "订单在手“心不慌”，轮胎企业海外扩产忙", "link": "https://36kr.com/newsflashes/2278153353811971?f=rss", "pubDate": "2023-05-29 08:17:25"}, {"title": "政策护航，国企加速“驶向”科创板", "link": "https://36kr.com/newsflashes/2278152526354185?f=rss", "pubDate": "2023-05-29 08:16:35"}, {"title": "淡马锡削减FTX相关投资团队及高级管理层薪酬", "link": "https://36kr.com/newsflashes/2278151592859648?f=rss", "pubDate": "2023-05-29 08:15:38"}, {"title": "A股蓄势待发，券商看好两条主线", "link": "https://36kr.com/newsflashes/2278149874309122?f=rss", "pubDate": "2023-05-29 08:13:53"}, {"title": "历史一刻！国产大飞机C919商业首飞成功", "link": "http://www.techweb.com.cn/it/2023-05-28/2927679.shtml", "pubDate": "2023-05-28 12:53:10"}, {"title": "AI成美股“万能药” 市场过度集中或带来风险", "link": "http://www.techweb.com.cn/it/2023-05-29/2927685.shtml", "pubDate": "2023-05-29 08:33:39"}, {"title": "余承东：没水平的人才打价格战 靠低价的车企很难走远", "link": "http://www.techweb.com.cn/it/2023-05-28/2927664.shtml", "pubDate": "2023-05-28 09:24:57"}, {"title": "知乎发布最新大模型应用“搜索聚合” 即日开启内测", "link": "http://www.techweb.com.cn/it/2023-05-28/2927659.shtml", "pubDate": "2023-05-28 09:10:23"}, {"title": "天涯回应无法访问：拖欠多年电信IDC费已无法协商", "link": "http://www.techweb.com.cn/it/2023-05-28/2927665.shtml", "pubDate": "2023-05-28 09:26:44"}, {"title": "48.6万起与轿车同价 奔驰EQE SUV上市：豪华电动车标杆", "link": "http://www.techweb.com.cn/smarttraveling/2023-05-28/2927663.shtml", "pubDate": "2023-05-28 09:22:27"}, {"title": "特斯拉被曝大规模数据泄露，含4000条“突然加速”投诉", "link": "http://www.techweb.com.cn/it/2023-05-28/2927682.shtml", "pubDate": "2023-05-28 12:59:30"}, {"title": "微软宣布Windows全球用户超10亿！Win11是史上最可靠操作系统", "link": "http://www.techweb.com.cn/it/2023-05-28/2927681.shtml", "pubDate": "2023-05-28 12:57:01"}, {"title": "苹果7月关闭我的照片流服务：用户需尽快迁移iCloud", "link": "http://www.techweb.com.cn/it/2023-05-28/2927672.shtml", "pubDate": "2023-05-28 10:35:42"}, {"title": "AMD等对手不足为惧 NVIDIA谈竞争优势：我们成本最低", "link": "http://www.techweb.com.cn/it/2023-05-28/2927675.shtml", "pubDate": "2023-05-28 10:44:51"}, {"title": "多人称被苹果充电头电伤 客服回应都在安全范围内", "link": "http://www.techweb.com.cn/it/2023-05-28/2927676.shtml", "pubDate": "2023-05-28 10:46:37"}, {"title": "把广告牌识别为真人后刹停 理想客服回应：具体原因需做分析诊断", "link": "http://www.techweb.com.cn/it/2023-05-28/2927674.shtml", "pubDate": "2023-05-28 10:39:39"}, {"title": "特斯拉：Model Y成为2023年第一季度全球最畅销车型", "link": "http://www.techweb.com.cn/smarttraveling/2023-05-27/2927642.shtml", "pubDate": "2023-05-27 09:10:13"}, {"title": "雷军：小米 13 Ultra 手机电商购买用户首月满意率超过 99%", "link": "http://www.techweb.com.cn/it/2023-05-27/2927643.shtml", "pubDate": "2023-05-27 09:12:41"}, {"title": "阿里云盘“永久有效分享”功能调整，6 月中旬起仅面向达人开放", "link": "http://www.techweb.com.cn/internet/2023-05-27/2927644.shtml", "pubDate": "2023-05-27 09:14:30"}, {"title": "特斯拉CEO马斯克：比亚迪的产品极具竞争力", "link": "http://www.techweb.com.cn/it/2023-05-28/2927662.shtml", "pubDate": "2023-05-28 09:17:45"}, {"title": "华为余承东：我喜欢做产品、不喜欢吹牛打广告", "link": "http://www.techweb.com.cn/it/2023-05-28/2927658.shtml", "pubDate": "2023-05-28 08:47:32"}, {"title": "周鸿祎训练数字人代替演讲！直言有危机感 不想被数字人“干掉”", "link": "http://www.techweb.com.cn/it/2023-05-28/2927673.shtml", "pubDate": "2023-05-28 10:37:33"}, {"title": "理想L系列芯片国产化率超25%！李想：不怕被黑 用中国本土供应商很自豪", "link": "http://www.techweb.com.cn/it/2023-05-26/2927564.shtml", "pubDate": "2023-05-26 09:19:11"}, {"title": "Meta继续与苹果“开战”？Quest 3或将成为苹果混合现实头显最大挑战者", "link": "http://www.techweb.com.cn/it/2023-05-29/2927686.shtml", "pubDate": "2023-05-29 08:36:18"}]